{
  "project_info": {
    "project_number": "144917112266",
    "project_id": "logistics-management-26709",
    "storage_bucket": "logistics-management-26709.firebasestorage.app"
  },
  "client": [
    {
      "client_info": {
        "mobilesdk_app_id": "1:144917112266:android:34806a43a00f0f9fac9b33",
        "android_client_info": {
          "package_name": "com.example.logistics_management_android_native"
        }
      },
      "oauth_client": [],
      "api_key": [
        {
          "current_key": "AIzaSyCPFp1aarYkZP-W9nJMBGBhrGOQFRL7xnc"
        }
      ],
      "services": {
        "appinvite_service": {
          "other_platform_oauth_client": []
        }
      }
    },
    {
      "client_info": {
        "mobilesdk_app_id": "1:144917112266:android:4c2b2f00dc5d1003ac9b33",
        "android_client_info": {
          "package_name": "com.logistics_management_react_native.DeRemate"
        }
      },
      "oauth_client": [],
      "api_key": [
        {
          "current_key": "AIzaSyCPFp1aarYkZP-W9nJMBGBhrGOQFRL7xnc"
        }
      ],
      "services": {
        "appinvite_service": {
          "other_platform_oauth_client": []
        }
      }
    }
  ],
  "configuration_version": "1"
}